rs_mrt_dau_utilities/__init__.py
rs_mrt_dau_utilities/delay_meas/__init__.py
rs_mrt_dau_utilities/delay_meas/delay_meas.py
rs_mrt_dau_utilities/delay_meas/dev.py
rs_mrt_dau_utilities/ip_analysis/__init__.py
rs_mrt_dau_utilities/ip_analysis/ip_analysis.py
rs_mrt_dau_utilities/py.typed
rs_mrt_dau_utilities-0.5.0.dist-info/WHEEL
rs_mrt_dau_utilities-0.5.0.dist-info/METADATA
rs_mrt_dau_utilities-0.5.0.dist-info/RECORD
