Metadata-Version: 2.4
Name: rs-mrt-dau-utilities
Version: 0.5.0
Summary: Helpers to process and visualize measurement data from Rohde & Schwarz MRT DAU
Author: Didier Chagniot
Author-email: Didier Chagniot <didier.chagniot@rohde-schwarz.com>
License-Expression: MIT
Classifier: Development Status :: 5 - Production/Stable
Classifier: Intended Audience :: Developers
Classifier: Programming Language :: Python :: 3
Classifier: Programming Language :: Python :: 3.11
Classifier: Programming Language :: Python :: 3.12
Classifier: Programming Language :: Python :: 3.13
Requires-Dist: altair>=5.5.0
Requires-Dist: fast-json-normalize>=0.0.9
Requires-Dist: polars==1.35.2
Requires-Python: >=3.11
Project-URL: Documentation, https://rs-mrt-dau-utilities.readthedocs.io/
Project-URL: Repository, https://github.com/Rohde-Schwarz/rs-mrt-dau-utilities
